tylereq/__init__.py
tylereq/shapes.py
tylereq-0.1.4.dist-info/licenses/LICENSE
tylereq-0.1.4.dist-info/METADATA
tylereq-0.1.4.dist-info/WHEEL
tylereq-0.1.4.dist-info/top_level.txt
tylereq-0.1.4.dist-info/RECORD
