Metadata-Version: 2.4
Name: tylereq
Version: 0.1.4
Summary: A simple equations module made by Tyler
Author-email: tyleruploads <tyleruploads@yahoo.com>
License-Expression: MIT
Project-URL: Homepage, https://github.com/tyleruploads/tylereq/
Requires-Python: >=3.8
License-File: LICENSE
Dynamic: license-file
